litestar_playwright/__init__.py
litestar_playwright/_version.py
litestar_playwright/config.py
litestar_playwright/plugin.py
litestar_playwright/py.typed
litestar_playwright-0.1.0.dist-info/METADATA
litestar_playwright-0.1.0.dist-info/WHEEL
litestar_playwright-0.1.0.dist-info/licenses/LICENSE
litestar_playwright-0.1.0.dist-info/RECORD
