Metadata-Version: 2.4
Name: litestar-playwright
Version: 0.1.0
Summary: Playwright integration for Litestar.
Project-URL: changelog, https://github.com/hasansezertasan/litestar-playwright/blob/main/CHANGELOG.md
Project-URL: documentation, https://github.com/hasansezertasan/litestar-playwright#readme
Project-URL: homepage, https://github.com/hasansezertasan/litestar-playwright
Project-URL: issues, https://github.com/hasansezertasan/litestar-playwright/issues
Project-URL: releasenotes, https://github.com/hasansezertasan/litestar-playwright/releases
Project-URL: source, https://github.com/hasansezertasan/litestar-playwright.git
Author-email: Hasan Sezer Taşan <hasansezertasan@gmail.com>
Maintainer-email: Hasan Sezer Taşan <hasansezertasan@gmail.com>
License-Expression: MIT
License-File: LICENSE
Keywords: automation,browser,litestar,litestar-extension,litestar-playwright,litestar-plugin,playwright,testing
Classifier: Development Status :: 4 - Beta
Classifier: Intended Audience :: Developers
Classifier: Intended Audience :: Information Technology
Classifier: Intended Audience :: System Administrators
Classifier: License :: OSI Approved :: MIT License
Classifier: Operating System :: OS Independent
Classifier: Programming Language :: Python
Classifier: Programming Language :: Python :: 3
Classifier: Programming Language :: Python :: 3 :: Only
Classifier: Programming Language :: Python :: 3.8
Classifier: Programming Language :: Python :: 3.9
Classifier: Programming Language :: Python :: 3.10
Classifier: Programming Language :: Python :: 3.11
Classifier: Programming Language :: Python :: 3.12
Classifier: Programming Language :: Python :: 3.13
Classifier: Programming Language :: Python :: 3.14
Classifier: Programming Language :: Python :: Implementation :: CPython
Classifier: Programming Language :: Python :: Implementation :: PyPy
Classifier: Topic :: Internet
Classifier: Topic :: Internet :: WWW/HTTP :: Browsers
Classifier: Topic :: Software Development
Classifier: Topic :: Software Development :: Libraries
Classifier: Topic :: Software Development :: Libraries :: Python Modules
Classifier: Typing :: Typed
Requires-Python: >=3.8
Requires-Dist: litestar
Requires-Dist: playwright
